{
		"status": "Active",
		"deviceName": "Device Name",
        "deviceDesignGroup": "Device Design Group",
        "deviceProcessGroup": "Device Process Group",
        "deviceGroup": "Device Group",
        "waferSize": "Wafer Size (mm)",
        "crystalOrientation": "Crystal Orientation",
        "chipSizeX": "Chip Size X (μm)",
        "chipSizeY": "Chip Size Y (μm)",
        "chipArea": "Chip Area (μm²)",
        "chipLocationX": "Chip Location X (μm)",
        "chipLocationY": "Chip Location Y (μm)",
        "comment1": "Comment 1",
        "comment2": "Comment 2",
        "comment3": "Comment 3",
        "numberOfChips": "Number of chips",
        "finalGoodChipNumberStandardValue": "Final good product number standard value",
        "finalYieldStandardValue": "Final yield standard value",
        "waferUnitPrice": "Wafer unit price",
        "standardChipUnitPrice": "Standard chip unit price",
        "shotMapModel.reticleX" : "Number of chip impositions X",
        "shotMapModel.reticleY" : "Number of chips impositions Y",
        "shotMapModel.shotSizeX" : "Exposure X size",
        "shotMapModel.shotSizeY" : "Exposure Y size",
        "shotMapModel.reticleLocationX" : "Reticle coordinates X",
        "shotMapModel.reticleLocationY" : "Reticle coordinates Y",
        "shotMapModel.maskGroup" : "Mask group",
        "shotMapModel.nonEffectiveAreaInOuter" : "Peripheral ineffective area",
        "shotMapModel.shotFormationJudgmentOutside" : "Shot formation judgment outer circumference",
        "shotMapModel.shotFormationJudgmentChips" : "Shot formation judgment chip",
        "shotMapModel.maskProcess" : "Mask process",
        "referenceValueModel.testGoodChipNumberStandardValue" : "Standard number of good test products",
        "referenceValueModel.testGoodChipNumberUpperTarget" : "Above the target number of good test products",
        "referenceValueModel.testGoodChipNumberLowerTarget" : "Below the target number of good test products",
        "referenceValueModel.finalGoodChipNumberUpperTarget" : "Above the final product target value",
        "referenceValueModel.finalGoodChipNumberLowerTarget" : "Below the final product target value",	
        "referenceValueModel.testYieldStandardValue" : "Test yield reference value",
        "referenceValueModel.testYieldUpperTarget" : "Above the test yield target",
        "referenceValueModel.testYieldLowerTarget" : "Below the test yield target",
        "referenceValueModel.finalYieldUpperTarget" : "Above the final yield target",
        "referenceValueModel.finalYieldLowerTarget" : "Below the final yield target",
        "lastUpdatedDate" : "Data update date and time",
        "lastUpdatedUser" : "Data update user name"
        
    }